MANIFEST.in
README.txt
bootstrap.py
buildout.cfg
setup.cfg
setup.py
versions.cfg
docs/CONTRIBUTORS.txt
docs/HISTORY.txt
docs/INSTALL.txt
docs/LICENSE.GPL
docs/LICENSE.txt
unweb/__init__.py
unweb.watermark.egg-info/PKG-INFO
unweb.watermark.egg-info/SOURCES.txt
unweb.watermark.egg-info/dependency_links.txt
unweb.watermark.egg-info/entry_points.txt
unweb.watermark.egg-info/namespace_packages.txt
unweb.watermark.egg-info/not-zip-safe
unweb.watermark.egg-info/paster_plugins.txt
unweb.watermark.egg-info/requires.txt
unweb.watermark.egg-info/top_level.txt
unweb/watermark/__init__.py
unweb/watermark/configure.zcml
unweb/watermark/controlpanel.py
unweb/watermark/extender.py
unweb/watermark/interfaces.py
unweb/watermark/permissions.zcml
unweb/watermark/profiles.zcml
unweb/watermark/subscribers.py
unweb/watermark/tests.py
unweb/watermark/profiles/default/controlpanel.xml
unweb/watermark/profiles/default/metadata.xml
unweb/watermark/profiles/default/registry.xml
unweb/watermark/profiles/default/rolemap.xml
unweb/watermark/profiles/default/workflows.xml