Metadata-Version: 1.0
Name: unweb.watermark
Version: 0.3
Summary: Support for adding watermarks to images
Home-page: http://svn.plone.org/svn/collective/unweb.watermark/
Author: unweb.me
Author-email: we@unweb.me
License: GPL
Keywords: image photo watermark plone zope
Platform: UNKNOWN
Classifier: Framework :: Plone
Classifier: Programming Language :: Python
Classifier: Topic :: Multimedia :: Graphics
